ode_parameter_estimator/__init__.py
ode_parameter_estimator/estimator.py
ode_parameter_estimator-1.0.dist-info/METADATA
ode_parameter_estimator-1.0.dist-info/WHEEL
ode_parameter_estimator-1.0.dist-info/licenses/LICENSE
ode_parameter_estimator-1.0.dist-info/RECORD
