Metadata-Version: 2.1
Name: ode_parameter_estimator
Version: 1.0
Summary: General ODE system parameter estimator using scipy
Project-URL: Homepage, https://github.com/JacobHilbert/ode-parameter-estimator
Author-email: Jacob Hilbert <jacob.hilbert.tree@gmail.com>
License-File: LICENSE
Classifier: License :: OSI Approved :: MIT License
Classifier: Operating System :: OS Independent
Classifier: Programming Language :: Python :: 3
Requires-Python: >=3.7
